palmiche/__init__.py
palmiche/_version.py
palmiche/cli.py
palmiche/home.py
palmiche/docking/__init__.py
palmiche/docking/box.py
palmiche/docking/dlg.py
palmiche/docking/vina.py
palmiche/docking/vscreening.py
palmiche/simultemp/__init__.py
palmiche/simultemp/water.py
palmiche/simultemp/weights.py
palmiche/umbrella/COM_distance.py
palmiche/umbrella/__init__.py
palmiche/umbrella/automation.py
palmiche/umbrella/automation_reverse.py
palmiche/umbrella/block_time_average.py
palmiche/umbrella/concat.py
palmiche/umbrella/conf_windows.py
palmiche/umbrella/ic50.py
palmiche/umbrella/make_posre.py
palmiche/umbrella/pmf.py
palmiche/umbrella/pmf_5ave.py
palmiche/umbrella/wham.py
palmiche/umbrella/wham_general.py
palmiche/utils/HMR_maker.py
palmiche/utils/__init__.py
palmiche/utils/assembleMD.py
palmiche/utils/autocorr.py
palmiche/utils/gmxtrjconv.py
palmiche/utils/gro.py
palmiche/utils/heavyh.py
palmiche/utils/jobsh.py
palmiche/utils/markov.py
palmiche/utils/mdp.py
palmiche/utils/pKa2pdb2gmx.py
palmiche/utils/pdb.py
palmiche/utils/potentials.py
palmiche/utils/test_pot.py
palmiche/utils/tools.py
palmiche/utils/xvg.py
palmiche-0.0.0a4.dist-info/LICENSE
palmiche-0.0.0a4.dist-info/METADATA
palmiche-0.0.0a4.dist-info/WHEEL
palmiche-0.0.0a4.dist-info/entry_points.txt
palmiche-0.0.0a4.dist-info/top_level.txt
palmiche-0.0.0a4.dist-info/RECORD
