Metadata-Version: 2.1
Name: palmiche
Version: 0.0.0a4
Summary: A python package for automation of MD simulations
Home-page: https://github.com/ale94mleon/palmiche
Author: Alejandro Martínez León
Author-email: ale94mleon@gmail.com
License: Apache License 2.0
Project-URL: Discussions, https://github.com/ale94mleon/palmiche/discussions
Project-URL: Documentation, https://palmiche.readthedocs.io/en/latest/
Project-URL: Issues, https://github.com/ale94mleon/palmiche/issues
Keywords: science,chemistry,biology
Platform: linux
Classifier: Development Status :: 2 - Pre-Alpha
Classifier: Operating System :: POSIX :: Linux
Classifier: Intended Audience :: Science/Research
Classifier: License :: OSI Approved :: Apache Software License
Classifier: Programming Language :: Python :: 3
Classifier: Programming Language :: Python :: 3.8
Classifier: Programming Language :: Python :: 3.9
Classifier: Programming Language :: Python :: 3.10
Classifier: Topic :: Scientific/Engineering :: Bio-Informatics
Classifier: Topic :: Scientific/Engineering :: Chemistry
Classifier: Topic :: Scientific/Engineering :: Physics
Requires-Python: <4,>=3.8
License-File: LICENSE
Requires-Dist: pubchempy
Requires-Dist: tqdm
Requires-Dist: numpy
Requires-Dist: pandas
Requires-Dist: sklearn
Requires-Dist: kmodes
Requires-Dist: kneed
Requires-Dist: uncertainties
Requires-Dist: prolif
Requires-Dist: scipy
Requires-Dist: rdkit
Requires-Dist: seaborn
Provides-Extra: test
Requires-Dist: pytest ; extra == 'test'
Requires-Dist: attrs ; extra == 'test'
